[
  {
    "name": "hotdogs",
    "ingredients": [
      "hot dog sausages ",
      "hot dog sausages ",
      "bread rolls",
      "onion",
      "tomato sauce",
      "mustard"
    ]
  },
  {
    "name": "lasagne",
    "ingredients": [
      "mince",
      "jar of red lasagne sauce",
      "tomato passata",
      "onion",
      "italian herbs",
      "garlic",
      "beef stock cube",
      "lasagne sheets",
      "white sauce",
      "garlic baguette",
      "garlic baguette"
    ]
  },
  {
    "name": "smoked fish",
    "ingredients": [
      "smoked fish",
      "new potatoes",
      "paprika",
      "garlic granules",
      "frozen sweetcorn"
    ]
  },
  {
    "name": "marmite potatos",
    "ingredients": ["potatoes", "marmite", "chicken kievs", "frozen sweetcorn"]
  },
  {
    "name": "burgers",
    "ingredients": [
      "burgers",
      "burger buns",
      "burger sauce",
      "gherkins",
      "potatoes",
      "carrots",
      "red cabbage",
      "white cabbage",
      "red onion",
      "mayo"
    ]
  },
  {
    "name": "stew and dumplings",
    "ingredients": [
      "diced beef",
      "mince",
      "beef stock cube",
      "gravy granuels",
      "stew vegetable pack",
      "potatoes",
      "garlic",
      "dumpling pack",
      "dumpling pack"
    ]
  },
  {
    "name": "pie and mash",
    "ingredients": [
      "pies",
      "potatoes",
      "milk",
      "butter",
      "gravy granuels",
      "yorkshire puddings",
      "frozen mushypeas"
    ]
  },
  {
    "name": "chicken roast",
    "ingredients": [
      "large whole chicken",
      "stuffing",
      "gravy granuels",
      "butternut squash",
      "garlic",
      "broccoli",
      "carrots",
      "leeks",
      "garlic and herb soft cheese",
      "double cream",
      "honey",
      "potatoes"
    ]
  },
  {
    "name": "gammon eggs",
    "ingredients": ["gammon joint", "eggs", "potatoes"]
  },
  {
    "name": "spaghetti bolognese",
    "ingredients": [
      "mince",
      "onion",
      "garlic",
      "cheese",
      "bolognese sauce",
      "tomato passata",
      "italian herbs",
      "spaghetti pasta"
    ]
  },
  {
    "name": "sausage and mash",
    "ingredients": [
      "chipolata",
      "potatoes",
      "butter",
      "milk",
      "gravy granuels",
      "red onion",
      "red wine stock pot",
      "green veg"
    ]
  },
  {
    "name": "sausages pasta",
    "ingredients": [
      "sausages",
      "pasta",
      "jar of pasta sauce",
      "chopped tomatoes",
      "italian herbs"
    ]
  },
  {
    "name": "bbq honey sausage",
    "ingredients": [
      "bbq sauce",
      "honey and pork sausages",
      "new potatoes",
      "garlic granules",
      "frozen sweetcorn"
    ]
  },
  {
    "name": "tuna pasta bake",
    "ingredients": ["tuna", "pasta bake packet", "milk", "pasta", "cheese"]
  }
]
